onow/__init__.py
onow/bootstrap_gdrive.py
onow/history-read-large-file-chunks.py
onow/history.py
onow/history0.py
onow/hypertable.py
onow/numericize_attributes.py
onow-0.0.1.dist-info/WHEEL
onow-0.0.1.dist-info/METADATA
onow-0.0.1.dist-info/RECORD
