Metadata-Version: 2.1
Name: onow
Version: 0.0.1
Summary: Tools for chatbot data science.
License: Hippocratic (MIT + Do No Harm)
Author: Tangible AI
Author-email: engineering@tangibleai.com
Requires-Python: >=3.7.1,<4.0
Classifier: License :: Other/Proprietary License
Classifier: Programming Language :: Python :: 3
Classifier: Programming Language :: Python :: 3.8
Classifier: Programming Language :: Python :: 3.9
Requires-Dist: pandas (>=1.2.4,<1.3.0)
Requires-Dist: scikit-learn (>=0.24.2,<0.25.0)
Requires-Dist: spacy (>=3.0.6,<3.1.0)
Requires-Dist: torch (>=1.8.1,<1.9.0)
Requires-Dist: torchtext (>=0.9.1,<0.10.0)
